{
    "expand": "schema,names",
    "startAt": 0,
    "maxResults": 50,
    "total": 3,
    "issues": [{
            "expand": "operations,versionedRepresentations,editmeta,changelog,renderedFields",
            "id": "15069",
            "self": "https://oncprojectracking.ahrqdev.org/support-jsd/rest/api/2/issue/15069",
            "key": "R4SDR-91",
            "fields": {
                "parent": {
                    "id": "15066",
                    "key": "R4SDR-88",
                    "self": "https://oncprojectracking.ahrqdev.org/support-jsd/rest/api/2/issue/15066",
                    "fields": {
                        "summary": "Direct review test",
                        "status": {
                            "self": "https://oncprojectracking.ahrqdev.org/support-jsd/rest/api/2/status/1",
                            "description": "The issue is open and ready for the assignee to start work on it.",
                            "iconUrl": "https://oncprojectracking.ahrqdev.org/support-jsd/images/icons/statuses/open.png",
                            "name": "Open",
                            "id": "1",
                            "statusCategory": {
                                "self": "https://oncprojectracking.ahrqdev.org/support-jsd/rest/api/2/statuscategory/2",
                                "id": 2,
                                "key": "new",
                                "colorName": "blue-gray",
                                "name": "To Do"
                            }
                        },
                        "priority": {
                            "self": "https://oncprojectracking.ahrqdev.org/support-jsd/rest/api/2/priority/3",
                            "iconUrl": "https://oncprojectracking.ahrqdev.org/support-jsd/images/icons/priorities/medium.svg",
                            "name": "Medium",
                            "id": "3"
                        },
                        "issuetype": {
                            "self": "https://oncprojectracking.ahrqdev.org/support-jsd/rest/api/2/issuetype/10104",
                            "id": "10104",
                            "description": "",
                            "iconUrl": "https://oncprojectracking.ahrqdev.org/support-jsd/secure/viewavatar?size=xsmall&avatarId=10300&avatarType=issuetype",
                            "name": "Direct Review",
                            "subtask": false,
                            "avatarId": 10300
                        }
                    }
                },
                "fixVersions": [],
                "resolution": null,
                "customfield_10104": null,
                "customfield_10500": null,
                "customfield_10105": null,
                "customfield_10501": null,
                "customfield_10900": null,
                "customfield_10901": null,
                "customfield_10902": null,
                "customfield_10903": null,
                "customfield_10904": null,
                "customfield_10905": null,
                "customfield_10906": null,
                "customfield_10907": null,
                "customfield_10908": null,
                "customfield_10909": null,
                "lastViewed": "2020-06-30T19:37:17.650+0000",
                "customfield_10100": null,
                "priority": {
                    "self": "https://oncprojectracking.ahrqdev.org/support-jsd/rest/api/2/priority/3",
                    "iconUrl": "https://oncprojectracking.ahrqdev.org/support-jsd/images/icons/priorities/medium.svg",
                    "name": "Medium",
                    "id": "3"
                },
                "customfield_10101": null,
                "customfield_10102": null,
                "customfield_10103": null,
                "labels": [],
                "customfield_10214": "No CHPL ID Provided\n",
                "customfield_10610": null,
                "customfield_10215": "No CHPL ID Provided\n",
                "customfield_10216": "No CHPL ID Provided\n",
                "customfield_10217": null,
                "customfield_10218": null,
                "timeestimate": null,
                "aggregatetimeoriginalestimate": null,
                "versions": [],
                "customfield_10219": null,
                "issuelinks": [],
                "assignee": null,
                "status": {
                    "self": "https://oncprojectracking.ahrqdev.org/support-jsd/rest/api/2/status/1",
                    "description": "The issue is open and ready for the assignee to start work on it.",
                    "iconUrl": "https://oncprojectracking.ahrqdev.org/support-jsd/images/icons/statuses/open.png",
                    "name": "Open",
                    "id": "1",
                    "statusCategory": {
                        "self": "https://oncprojectracking.ahrqdev.org/support-jsd/rest/api/2/statuscategory/2",
                        "id": 2,
                        "key": "new",
                        "colorName": "blue-gray",
                        "name": "To Do"
                    }
                },
                "components": [],
                "customfield_10210": null,
                "customfield_10211": null,
                "customfield_10212": "No CHPL ID Provided\n",
                "customfield_10213": null,
                "customfield_10203": null,
                "customfield_10204": null,
                "customfield_10600": null,
                "customfield_10205": null,
                "customfield_10601": null,
                "customfield_10206": null,
                "customfield_10602": null,
                "customfield_10207": null,
                "customfield_10603": null,
                "aggregatetimeestimate": null,
                "customfield_10208": null,
                "customfield_10604": null,
                "customfield_10209": null,
                "customfield_10605": null,
                "customfield_10606": null,
                "customfield_10607": null,
                "customfield_10608": null,
                "customfield_10609": "{\"asFlag\":false,\"isEmpty\":false,\"fieldId\":\"10609\",\"messageType\":\"info\",\"isSimpleView\":false,\"title\":\"\",\"body\":\"<style>\\r\\n\\r\\n.loader {\\r\\n  border: 16px solid #f3f3f3; /* Light grey */\\r\\n  border-top: 16px solid #3498db; /* Blue */\\r\\n  border-radius: 50%;\\r\\n  width: 80px;\\r\\n  height: 80px;\\r\\n  animation: spin 2s linear infinite;\\r\\n  margin-left: auto;\\r\\n  margin-right: auto;\\r\\n}\\r\\n\\r\\n@keyframes spin {\\r\\n  0% { transform: rotate(0deg); }\\r\\n  100% { transform: rotate(360deg); }\\r\\n}\\r\\n\\r\\n<\\/style>\\r\\n\\r\\n<div class=\\\"loader\\\"><\\/div>\\r\\n\\r\\n\",\"selector\":\"\",\"jibrokMessageKey\":\"true\",\"codeContexts\":\"CREATE_SD\",\"CREATE_SD\":true,\"VIEW_SD\":false,\"code\":\"require(['jquery'], function($) {\\r\\n\\t\\r\\n\\t$(\\\".aui-message-info\\\").css('width', '100%');\\r\\n\\r\\n\\r\\nwindow.top.location.href = \\\"https://www.healthit.gov/curesrule/final-rule-policy/information-blocking/report\\\"; \\r\\n\\t\\r\\n})\"}",
                "creator": {
                    "self": "https://oncprojectracking.ahrqdev.org/support-jsd/rest/api/2/user?username=zmiller",
                    "name": "zmiller",
                    "key": "JIRAUSER10000",
                    "emailAddress": "zmiller@ainq.com",
                    "avatarUrls": {
                        "48x48": "https://oncprojectracking.ahrqdev.org/support-jsd/secure/useravatar?ownerId=JIRAUSER10000&avatarId=10800",
                        "24x24": "https://oncprojectracking.ahrqdev.org/support-jsd/secure/useravatar?size=small&ownerId=JIRAUSER10000&avatarId=10800",
                        "16x16": "https://oncprojectracking.ahrqdev.org/support-jsd/secure/useravatar?size=xsmall&ownerId=JIRAUSER10000&avatarId=10800",
                        "32x32": "https://oncprojectracking.ahrqdev.org/support-jsd/secure/useravatar?size=medium&ownerId=JIRAUSER10000&avatarId=10800"
                    },
                    "displayName": "Zachary Miller",
                    "active": true,
                    "timeZone": "America/New_York"
                },
                "subtasks": [],
                "reporter": {
                    "self": "https://oncprojectracking.ahrqdev.org/support-jsd/rest/api/2/user?username=zmiller",
                    "name": "zmiller",
                    "key": "JIRAUSER10000",
                    "emailAddress": "zmiller@ainq.com",
                    "avatarUrls": {
                        "48x48": "https://oncprojectracking.ahrqdev.org/support-jsd/secure/useravatar?ownerId=JIRAUSER10000&avatarId=10800",
                        "24x24": "https://oncprojectracking.ahrqdev.org/support-jsd/secure/useravatar?size=small&ownerId=JIRAUSER10000&avatarId=10800",
                        "16x16": "https://oncprojectracking.ahrqdev.org/support-jsd/secure/useravatar?size=xsmall&ownerId=JIRAUSER10000&avatarId=10800",
                        "32x32": "https://oncprojectracking.ahrqdev.org/support-jsd/secure/useravatar?size=medium&ownerId=JIRAUSER10000&avatarId=10800"
                    },
                    "displayName": "Zachary Miller",
                    "active": true,
                    "timeZone": "America/New_York"
                },
                "aggregateprogress": {
                    "progress": 0,
                    "total": 0
                },
                "customfield_10200": null,
                "customfield_10201": null,
                "customfield_10202": {
                    "self": "https://oncprojectracking.ahrqdev.org/support-jsd/rest/api/2/customFieldOption/10001",
                    "value": "No",
                    "id": "10001"
                },
                "progress": {
                    "progress": 0,
                    "total": 0
                },
                "issuetype": {
                    "self": "https://oncprojectracking.ahrqdev.org/support-jsd/rest/api/2/issuetype/10303",
                    "id": "10303",
                    "description": "",
                    "iconUrl": "https://oncprojectracking.ahrqdev.org/support-jsd/secure/viewavatar?size=xsmall&avatarId=10316&avatarType=issuetype",
                    "name": "Requirement/Non-Conformity",
                    "subtask": true,
                    "avatarId": 10316
                },
                "timespent": null,
                "project": {
                    "self": "https://oncprojectracking.ahrqdev.org/support-jsd/rest/api/2/project/10103",
                    "id": "10103",
                    "key": "R4SDR",
                    "name": "Review for Signals/Direct Review",
                    "projectTypeKey": "service_desk",
                    "avatarUrls": {
                        "48x48": "https://oncprojectracking.ahrqdev.org/support-jsd/secure/projectavatar?avatarId=10324",
                        "24x24": "https://oncprojectracking.ahrqdev.org/support-jsd/secure/projectavatar?size=small&avatarId=10324",
                        "16x16": "https://oncprojectracking.ahrqdev.org/support-jsd/secure/projectavatar?size=xsmall&avatarId=10324",
                        "32x32": "https://oncprojectracking.ahrqdev.org/support-jsd/secure/projectavatar?size=medium&avatarId=10324"
                    }
                },
                "aggregatetimespent": null,
                "customfield_10940": "R4SDR-88",
                "customfield_10302": null,
                "customfield_10303": null,
                "customfield_10941": null,
                "customfield_10700": null,
                "customfield_10304": null,
                "customfield_10942": null,
                "customfield_10305": null,
                "customfield_10943": ["15.04.04.2913.Gree.11.00.1.171101"],
                "customfield_10306": null,
                "customfield_10944": {
                    "self": "https://oncprojectracking.ahrqdev.org/support-jsd/rest/api/2/customFieldOption/10870",
                    "value": "Non-Conformity Found",
                    "id": "10870"
                },
                "customfield_10307": null,
                "customfield_10945": null,
                "customfield_10308": null,
                "customfield_10946": null,
                "resolutiondate": null,
                "customfield_10309": null,
                "customfield_10947": null,
                "workratio": -1,
                "watches": {
                    "self": "https://oncprojectracking.ahrqdev.org/support-jsd/rest/api/2/issue/R4SDR-91/watchers",
                    "watchCount": 0,
                    "isWatching": false
                },
                "created": "2020-06-26T16:46:54.000+0000",
                "customfield_10300": null,
                "customfield_10412": null,
                "customfield_10413": null,
                "customfield_10930": "it's fixed!",
                "customfield_10931": null,
                "customfield_10932": null,
                "customfield_10933": {
                    "self": "https://oncprojectracking.ahrqdev.org/support-jsd/rest/api/2/customFieldOption/10753",
                    "value": "170.406(b)(1)",
                    "id": "10753"
                },
                "customfield_10934": {
                    "self": "https://oncprojectracking.ahrqdev.org/support-jsd/rest/api/2/customFieldOption/10788",
                    "value": "170.406(b)(1)",
                    "id": "10788"
                },
                "customfield_10935": {
                    "self": "https://oncprojectracking.ahrqdev.org/support-jsd/rest/api/2/customFieldOption/10790",
                    "value": "Closed",
                    "id": "10790"
                },
                "customfield_10936": {
                    "self": "https://oncprojectracking.ahrqdev.org/support-jsd/rest/api/2/customFieldOption/10792",
                    "value": "No",
                    "id": "10792"
                },
                "customfield_10937": null,
                "customfield_10938": null,
                "updated": "2020-06-30T13:28:15.000+0000",
                "timeoriginalestimate": null,
                "description": null,
                "customfield_10411": null,
                "customfield_10402": null,
                "security": {
                    "self": "https://oncprojectracking.ahrqdev.org/support-jsd/rest/api/2/securitylevel/10005",
                    "id": "10005",
                    "description": "",
                    "name": "Direct Review"
                },
                "customfield_10403": null,
                "customfield_10800": {
                    "self": "https://oncprojectracking.ahrqdev.org/support-jsd/rest/api/2/customFieldOption/10601",
                    "value": "No",
                    "id": "10601"
                },
                "customfield_10921": "2020-06-01",
                "customfield_10404": null,
                "customfield_10922": "2020-06-02",
                "customfield_10405": null,
                "customfield_10923": "2020-06-08",
                "customfield_10406": null,
                "customfield_10407": null,
                "customfield_10408": null,
                "customfield_10925": "2020-06-30",
                "customfield_10409": null,
                "customfield_10926": "2020-06-26",
                "customfield_10927": "test summary",
                "customfield_10928": "some findings",
                "customfield_10929": "an explanation by the developer",
                "summary": "Requirement of R4SDR-88",
                "customfield_10000": [],
                "customfield_10001": null,
                "customfield_10002": [],
                "customfield_10400": null,
                "environment": null,
                "customfield_10910": null,
                "customfield_10911": null,
                "customfield_10912": null,
                "duedate": null,
                "customfield_10913": null,
                "customfield_10914": null,
                "customfield_10915": null,
                "customfield_10916": null,
                "customfield_10917": null,
                "customfield_10918": null
            }
        }, {
            "expand": "operations,versionedRepresentations,editmeta,changelog,renderedFields",
            "id": "15068",
            "self": "https://oncprojectracking.ahrqdev.org/support-jsd/rest/api/2/issue/15068",
            "key": "R4SDR-90",
            "fields": {
                "parent": {
                    "id": "15066",
                    "key": "R4SDR-88",
                    "self": "https://oncprojectracking.ahrqdev.org/support-jsd/rest/api/2/issue/15066",
                    "fields": {
                        "summary": "Direct review test",
                        "status": {
                            "self": "https://oncprojectracking.ahrqdev.org/support-jsd/rest/api/2/status/1",
                            "description": "The issue is open and ready for the assignee to start work on it.",
                            "iconUrl": "https://oncprojectracking.ahrqdev.org/support-jsd/images/icons/statuses/open.png",
                            "name": "Open",
                            "id": "1",
                            "statusCategory": {
                                "self": "https://oncprojectracking.ahrqdev.org/support-jsd/rest/api/2/statuscategory/2",
                                "id": 2,
                                "key": "new",
                                "colorName": "blue-gray",
                                "name": "To Do"
                            }
                        },
                        "priority": {
                            "self": "https://oncprojectracking.ahrqdev.org/support-jsd/rest/api/2/priority/3",
                            "iconUrl": "https://oncprojectracking.ahrqdev.org/support-jsd/images/icons/priorities/medium.svg",
                            "name": "Medium",
                            "id": "3"
                        },
                        "issuetype": {
                            "self": "https://oncprojectracking.ahrqdev.org/support-jsd/rest/api/2/issuetype/10104",
                            "id": "10104",
                            "description": "",
                            "iconUrl": "https://oncprojectracking.ahrqdev.org/support-jsd/secure/viewavatar?size=xsmall&avatarId=10300&avatarType=issuetype",
                            "name": "Direct Review",
                            "subtask": false,
                            "avatarId": 10300
                        }
                    }
                },
                "fixVersions": [],
                "resolution": null,
                "customfield_10104": null,
                "customfield_10500": null,
                "customfield_10105": null,
                "customfield_10501": null,
                "customfield_10900": null,
                "customfield_10901": null,
                "customfield_10902": null,
                "customfield_10903": null,
                "customfield_10904": null,
                "customfield_10905": null,
                "customfield_10906": null,
                "customfield_10907": null,
                "customfield_10908": null,
                "customfield_10909": null,
                "lastViewed": "2020-06-30T13:28:40.452+0000",
                "customfield_10100": null,
                "priority": {
                    "self": "https://oncprojectracking.ahrqdev.org/support-jsd/rest/api/2/priority/3",
                    "iconUrl": "https://oncprojectracking.ahrqdev.org/support-jsd/images/icons/priorities/medium.svg",
                    "name": "Medium",
                    "id": "3"
                },
                "customfield_10101": null,
                "customfield_10102": null,
                "customfield_10103": null,
                "labels": [],
                "customfield_10214": "No CHPL ID Provided\n",
                "customfield_10610": null,
                "customfield_10215": "No CHPL ID Provided\n",
                "customfield_10216": "No CHPL ID Provided\n",
                "customfield_10217": null,
                "customfield_10218": null,
                "timeestimate": null,
                "aggregatetimeoriginalestimate": null,
                "versions": [],
                "customfield_10219": null,
                "issuelinks": [],
                "assignee": null,
                "status": {
                    "self": "https://oncprojectracking.ahrqdev.org/support-jsd/rest/api/2/status/1",
                    "description": "The issue is open and ready for the assignee to start work on it.",
                    "iconUrl": "https://oncprojectracking.ahrqdev.org/support-jsd/images/icons/statuses/open.png",
                    "name": "Open",
                    "id": "1",
                    "statusCategory": {
                        "self": "https://oncprojectracking.ahrqdev.org/support-jsd/rest/api/2/statuscategory/2",
                        "id": 2,
                        "key": "new",
                        "colorName": "blue-gray",
                        "name": "To Do"
                    }
                },
                "components": [],
                "customfield_10210": null,
                "customfield_10211": null,
                "customfield_10212": "No CHPL ID Provided\n",
                "customfield_10213": null,
                "customfield_10203": null,
                "customfield_10204": null,
                "customfield_10600": null,
                "customfield_10205": null,
                "customfield_10601": null,
                "customfield_10206": null,
                "customfield_10602": null,
                "customfield_10207": null,
                "customfield_10603": null,
                "aggregatetimeestimate": null,
                "customfield_10208": null,
                "customfield_10604": null,
                "customfield_10209": null,
                "customfield_10605": null,
                "customfield_10606": null,
                "customfield_10607": null,
                "customfield_10608": null,
                "customfield_10609": "{\"asFlag\":false,\"isEmpty\":false,\"fieldId\":\"10609\",\"messageType\":\"info\",\"isSimpleView\":false,\"title\":\"\",\"body\":\"<style>\\r\\n\\r\\n.loader {\\r\\n  border: 16px solid #f3f3f3; /* Light grey */\\r\\n  border-top: 16px solid #3498db; /* Blue */\\r\\n  border-radius: 50%;\\r\\n  width: 80px;\\r\\n  height: 80px;\\r\\n  animation: spin 2s linear infinite;\\r\\n  margin-left: auto;\\r\\n  margin-right: auto;\\r\\n}\\r\\n\\r\\n@keyframes spin {\\r\\n  0% { transform: rotate(0deg); }\\r\\n  100% { transform: rotate(360deg); }\\r\\n}\\r\\n\\r\\n<\\/style>\\r\\n\\r\\n<div class=\\\"loader\\\"><\\/div>\\r\\n\\r\\n\",\"selector\":\"\",\"jibrokMessageKey\":\"true\",\"codeContexts\":\"CREATE_SD\",\"CREATE_SD\":true,\"VIEW_SD\":false,\"code\":\"require(['jquery'], function($) {\\r\\n\\t\\r\\n\\t$(\\\".aui-message-info\\\").css('width', '100%');\\r\\n\\r\\n\\r\\nwindow.top.location.href = \\\"https://www.healthit.gov/curesrule/final-rule-policy/information-blocking/report\\\"; \\r\\n\\t\\r\\n})\"}",
                "creator": {
                    "self": "https://oncprojectracking.ahrqdev.org/support-jsd/rest/api/2/user?username=zmiller",
                    "name": "zmiller",
                    "key": "JIRAUSER10000",
                    "emailAddress": "zmiller@ainq.com",
                    "avatarUrls": {
                        "48x48": "https://oncprojectracking.ahrqdev.org/support-jsd/secure/useravatar?ownerId=JIRAUSER10000&avatarId=10800",
                        "24x24": "https://oncprojectracking.ahrqdev.org/support-jsd/secure/useravatar?size=small&ownerId=JIRAUSER10000&avatarId=10800",
                        "16x16": "https://oncprojectracking.ahrqdev.org/support-jsd/secure/useravatar?size=xsmall&ownerId=JIRAUSER10000&avatarId=10800",
                        "32x32": "https://oncprojectracking.ahrqdev.org/support-jsd/secure/useravatar?size=medium&ownerId=JIRAUSER10000&avatarId=10800"
                    },
                    "displayName": "Zachary Miller",
                    "active": true,
                    "timeZone": "America/New_York"
                },
                "subtasks": [],
                "reporter": {
                    "self": "https://oncprojectracking.ahrqdev.org/support-jsd/rest/api/2/user?username=zmiller",
                    "name": "zmiller",
                    "key": "JIRAUSER10000",
                    "emailAddress": "zmiller@ainq.com",
                    "avatarUrls": {
                        "48x48": "https://oncprojectracking.ahrqdev.org/support-jsd/secure/useravatar?ownerId=JIRAUSER10000&avatarId=10800",
                        "24x24": "https://oncprojectracking.ahrqdev.org/support-jsd/secure/useravatar?size=small&ownerId=JIRAUSER10000&avatarId=10800",
                        "16x16": "https://oncprojectracking.ahrqdev.org/support-jsd/secure/useravatar?size=xsmall&ownerId=JIRAUSER10000&avatarId=10800",
                        "32x32": "https://oncprojectracking.ahrqdev.org/support-jsd/secure/useravatar?size=medium&ownerId=JIRAUSER10000&avatarId=10800"
                    },
                    "displayName": "Zachary Miller",
                    "active": true,
                    "timeZone": "America/New_York"
                },
                "aggregateprogress": {
                    "progress": 0,
                    "total": 0
                },
                "customfield_10200": null,
                "customfield_10201": null,
                "customfield_10202": {
                    "self": "https://oncprojectracking.ahrqdev.org/support-jsd/rest/api/2/customFieldOption/10001",
                    "value": "No",
                    "id": "10001"
                },
                "progress": {
                    "progress": 0,
                    "total": 0
                },
                "issuetype": {
                    "self": "https://oncprojectracking.ahrqdev.org/support-jsd/rest/api/2/issuetype/10303",
                    "id": "10303",
                    "description": "",
                    "iconUrl": "https://oncprojectracking.ahrqdev.org/support-jsd/secure/viewavatar?size=xsmall&avatarId=10316&avatarType=issuetype",
                    "name": "Requirement/Non-Conformity",
                    "subtask": true,
                    "avatarId": 10316
                },
                "timespent": null,
                "project": {
                    "self": "https://oncprojectracking.ahrqdev.org/support-jsd/rest/api/2/project/10103",
                    "id": "10103",
                    "key": "R4SDR",
                    "name": "Review for Signals/Direct Review",
                    "projectTypeKey": "service_desk",
                    "avatarUrls": {
                        "48x48": "https://oncprojectracking.ahrqdev.org/support-jsd/secure/projectavatar?avatarId=10324",
                        "24x24": "https://oncprojectracking.ahrqdev.org/support-jsd/secure/projectavatar?size=small&avatarId=10324",
                        "16x16": "https://oncprojectracking.ahrqdev.org/support-jsd/secure/projectavatar?size=xsmall&avatarId=10324",
                        "32x32": "https://oncprojectracking.ahrqdev.org/support-jsd/secure/projectavatar?size=medium&avatarId=10324"
                    }
                },
                "aggregatetimespent": null,
                "customfield_10940": null,
                "customfield_10302": null,
                "customfield_10303": null,
                "customfield_10941": null,
                "customfield_10700": null,
                "customfield_10304": null,
                "customfield_10942": null,
                "customfield_10305": null,
                "customfield_10943": ["15.02.02.3007.A056.01.00.0.180214"],
                "customfield_10306": null,
                "customfield_10944": {
                    "self": "https://oncprojectracking.ahrqdev.org/support-jsd/rest/api/2/customFieldOption/10870",
                    "value": "Non-Conformity Found",
                    "id": "10870"
                },
                "customfield_10307": null,
                "customfield_10945": null,
                "customfield_10308": null,
                "customfield_10946": null,
                "resolutiondate": null,
                "customfield_10309": null,
                "customfield_10947": null,
                "workratio": -1,
                "watches": {
                    "self": "https://oncprojectracking.ahrqdev.org/support-jsd/rest/api/2/issue/R4SDR-90/watchers",
                    "watchCount": 0,
                    "isWatching": false
                },
                "created": "2020-06-26T16:44:47.000+0000",
                "customfield_10300": null,
                "customfield_10412": null,
                "customfield_10413": null,
                "customfield_10930": null,
                "customfield_10931": null,
                "customfield_10932": null,
                "customfield_10933": {
                    "self": "https://oncprojectracking.ahrqdev.org/support-jsd/rest/api/2/customFieldOption/10735",
                    "value": "170.404(b)(2)",
                    "id": "10735"
                },
                "customfield_10934": {
                    "self": "https://oncprojectracking.ahrqdev.org/support-jsd/rest/api/2/customFieldOption/10764",
                    "value": "170.403(b)(2)",
                    "id": "10764"
                },
                "customfield_10935": {
                    "self": "https://oncprojectracking.ahrqdev.org/support-jsd/rest/api/2/customFieldOption/10789",
                    "value": "Open",
                    "id": "10789"
                },
                "customfield_10936": {
                    "self": "https://oncprojectracking.ahrqdev.org/support-jsd/rest/api/2/customFieldOption/10792",
                    "value": "No",
                    "id": "10792"
                },
                "customfield_10937": null,
                "customfield_10938": null,
                "updated": "2020-06-30T13:28:40.000+0000",
                "timeoriginalestimate": null,
                "description": null,
                "customfield_10411": null,
                "customfield_10402": null,
                "security": {
                    "self": "https://oncprojectracking.ahrqdev.org/support-jsd/rest/api/2/securitylevel/10005",
                    "id": "10005",
                    "description": "",
                    "name": "Direct Review"
                },
                "customfield_10403": null,
                "customfield_10800": {
                    "self": "https://oncprojectracking.ahrqdev.org/support-jsd/rest/api/2/customFieldOption/10601",
                    "value": "No",
                    "id": "10601"
                },
                "customfield_10921": "2020-06-24",
                "customfield_10404": null,
                "customfield_10922": "2020-06-25",
                "customfield_10405": null,
                "customfield_10923": "2020-06-25",
                "customfield_10406": null,
                "customfield_10407": null,
                "customfield_10408": null,
                "customfield_10925": "2020-07-31",
                "customfield_10409": null,
                "customfield_10926": null,
                "customfield_10927": "A nonconformity was found",
                "customfield_10928": null,
                "customfield_10929": null,
                "summary": "Requirement of R4SDR-88",
                "customfield_10000": [],
                "customfield_10001": null,
                "customfield_10002": [],
                "customfield_10400": null,
                "environment": null,
                "customfield_10910": null,
                "customfield_10911": null,
                "customfield_10912": null,
                "duedate": null,
                "customfield_10913": null,
                "customfield_10914": null,
                "customfield_10915": null,
                "customfield_10916": null,
                "customfield_10917": null,
                "customfield_10918": null
            }
        }, {
            "expand": "operations,versionedRepresentations,editmeta,changelog,renderedFields",
            "id": "15067",
            "self": "https://oncprojectracking.ahrqdev.org/support-jsd/rest/api/2/issue/15067",
            "key": "R4SDR-89",
            "fields": {
                "parent": {
                    "id": "15066",
                    "key": "R4SDR-88",
                    "self": "https://oncprojectracking.ahrqdev.org/support-jsd/rest/api/2/issue/15066",
                    "fields": {
                        "summary": "Direct review test",
                        "status": {
                            "self": "https://oncprojectracking.ahrqdev.org/support-jsd/rest/api/2/status/1",
                            "description": "The issue is open and ready for the assignee to start work on it.",
                            "iconUrl": "https://oncprojectracking.ahrqdev.org/support-jsd/images/icons/statuses/open.png",
                            "name": "Open",
                            "id": "1",
                            "statusCategory": {
                                "self": "https://oncprojectracking.ahrqdev.org/support-jsd/rest/api/2/statuscategory/2",
                                "id": 2,
                                "key": "new",
                                "colorName": "blue-gray",
                                "name": "To Do"
                            }
                        },
                        "priority": {
                            "self": "https://oncprojectracking.ahrqdev.org/support-jsd/rest/api/2/priority/3",
                            "iconUrl": "https://oncprojectracking.ahrqdev.org/support-jsd/images/icons/priorities/medium.svg",
                            "name": "Medium",
                            "id": "3"
                        },
                        "issuetype": {
                            "self": "https://oncprojectracking.ahrqdev.org/support-jsd/rest/api/2/issuetype/10104",
                            "id": "10104",
                            "description": "",
                            "iconUrl": "https://oncprojectracking.ahrqdev.org/support-jsd/secure/viewavatar?size=xsmall&avatarId=10300&avatarType=issuetype",
                            "name": "Direct Review",
                            "subtask": false,
                            "avatarId": 10300
                        }
                    }
                },
                "fixVersions": [],
                "resolution": null,
                "customfield_10104": null,
                "customfield_10500": null,
                "customfield_10105": null,
                "customfield_10501": null,
                "customfield_10900": null,
                "customfield_10901": null,
                "customfield_10902": null,
                "customfield_10903": null,
                "customfield_10904": null,
                "customfield_10905": null,
                "customfield_10906": null,
                "customfield_10907": null,
                "customfield_10908": null,
                "customfield_10909": null,
                "lastViewed": "2020-06-30T13:29:35.135+0000",
                "customfield_10100": null,
                "priority": {
                    "self": "https://oncprojectracking.ahrqdev.org/support-jsd/rest/api/2/priority/3",
                    "iconUrl": "https://oncprojectracking.ahrqdev.org/support-jsd/images/icons/priorities/medium.svg",
                    "name": "Medium",
                    "id": "3"
                },
                "customfield_10101": null,
                "customfield_10102": null,
                "customfield_10103": null,
                "labels": [],
                "customfield_10214": "No CHPL ID Provided\n",
                "customfield_10610": null,
                "customfield_10215": "No CHPL ID Provided\n",
                "customfield_10216": "No CHPL ID Provided\n",
                "customfield_10217": null,
                "customfield_10218": null,
                "timeestimate": null,
                "aggregatetimeoriginalestimate": null,
                "versions": [],
                "customfield_10219": null,
                "issuelinks": [],
                "assignee": null,
                "status": {
                    "self": "https://oncprojectracking.ahrqdev.org/support-jsd/rest/api/2/status/1",
                    "description": "The issue is open and ready for the assignee to start work on it.",
                    "iconUrl": "https://oncprojectracking.ahrqdev.org/support-jsd/images/icons/statuses/open.png",
                    "name": "Open",
                    "id": "1",
                    "statusCategory": {
                        "self": "https://oncprojectracking.ahrqdev.org/support-jsd/rest/api/2/statuscategory/2",
                        "id": 2,
                        "key": "new",
                        "colorName": "blue-gray",
                        "name": "To Do"
                    }
                },
                "components": [],
                "customfield_10210": null,
                "customfield_10211": null,
                "customfield_10212": "No CHPL ID Provided\n",
                "customfield_10213": null,
                "customfield_10203": null,
                "customfield_10204": null,
                "customfield_10600": null,
                "customfield_10205": null,
                "customfield_10601": null,
                "customfield_10206": null,
                "customfield_10602": null,
                "customfield_10207": null,
                "customfield_10603": null,
                "aggregatetimeestimate": null,
                "customfield_10208": null,
                "customfield_10604": null,
                "customfield_10209": null,
                "customfield_10605": null,
                "customfield_10606": null,
                "customfield_10607": null,
                "customfield_10608": null,
                "customfield_10609": "{\"asFlag\":false,\"isEmpty\":false,\"fieldId\":\"10609\",\"messageType\":\"info\",\"isSimpleView\":false,\"title\":\"\",\"body\":\"<style>\\r\\n\\r\\n.loader {\\r\\n  border: 16px solid #f3f3f3; /* Light grey */\\r\\n  border-top: 16px solid #3498db; /* Blue */\\r\\n  border-radius: 50%;\\r\\n  width: 80px;\\r\\n  height: 80px;\\r\\n  animation: spin 2s linear infinite;\\r\\n  margin-left: auto;\\r\\n  margin-right: auto;\\r\\n}\\r\\n\\r\\n@keyframes spin {\\r\\n  0% { transform: rotate(0deg); }\\r\\n  100% { transform: rotate(360deg); }\\r\\n}\\r\\n\\r\\n<\\/style>\\r\\n\\r\\n<div class=\\\"loader\\\"><\\/div>\\r\\n\\r\\n\",\"selector\":\"\",\"jibrokMessageKey\":\"true\",\"codeContexts\":\"CREATE_SD\",\"CREATE_SD\":true,\"VIEW_SD\":false,\"code\":\"require(['jquery'], function($) {\\r\\n\\t\\r\\n\\t$(\\\".aui-message-info\\\").css('width', '100%');\\r\\n\\r\\n\\r\\nwindow.top.location.href = \\\"https://www.healthit.gov/curesrule/final-rule-policy/information-blocking/report\\\"; \\r\\n\\t\\r\\n})\"}",
                "creator": {
                    "self": "https://oncprojectracking.ahrqdev.org/support-jsd/rest/api/2/user?username=zmiller",
                    "name": "zmiller",
                    "key": "JIRAUSER10000",
                    "emailAddress": "zmiller@ainq.com",
                    "avatarUrls": {
                        "48x48": "https://oncprojectracking.ahrqdev.org/support-jsd/secure/useravatar?ownerId=JIRAUSER10000&avatarId=10800",
                        "24x24": "https://oncprojectracking.ahrqdev.org/support-jsd/secure/useravatar?size=small&ownerId=JIRAUSER10000&avatarId=10800",
                        "16x16": "https://oncprojectracking.ahrqdev.org/support-jsd/secure/useravatar?size=xsmall&ownerId=JIRAUSER10000&avatarId=10800",
                        "32x32": "https://oncprojectracking.ahrqdev.org/support-jsd/secure/useravatar?size=medium&ownerId=JIRAUSER10000&avatarId=10800"
                    },
                    "displayName": "Zachary Miller",
                    "active": true,
                    "timeZone": "America/New_York"
                },
                "subtasks": [],
                "reporter": {
                    "self": "https://oncprojectracking.ahrqdev.org/support-jsd/rest/api/2/user?username=zmiller",
                    "name": "zmiller",
                    "key": "JIRAUSER10000",
                    "emailAddress": "zmiller@ainq.com",
                    "avatarUrls": {
                        "48x48": "https://oncprojectracking.ahrqdev.org/support-jsd/secure/useravatar?ownerId=JIRAUSER10000&avatarId=10800",
                        "24x24": "https://oncprojectracking.ahrqdev.org/support-jsd/secure/useravatar?size=small&ownerId=JIRAUSER10000&avatarId=10800",
                        "16x16": "https://oncprojectracking.ahrqdev.org/support-jsd/secure/useravatar?size=xsmall&ownerId=JIRAUSER10000&avatarId=10800",
                        "32x32": "https://oncprojectracking.ahrqdev.org/support-jsd/secure/useravatar?size=medium&ownerId=JIRAUSER10000&avatarId=10800"
                    },
                    "displayName": "Zachary Miller",
                    "active": true,
                    "timeZone": "America/New_York"
                },
                "aggregateprogress": {
                    "progress": 0,
                    "total": 0
                },
                "customfield_10200": null,
                "customfield_10201": null,
                "customfield_10202": {
                    "self": "https://oncprojectracking.ahrqdev.org/support-jsd/rest/api/2/customFieldOption/10001",
                    "value": "No",
                    "id": "10001"
                },
                "progress": {
                    "progress": 0,
                    "total": 0
                },
                "issuetype": {
                    "self": "https://oncprojectracking.ahrqdev.org/support-jsd/rest/api/2/issuetype/10303",
                    "id": "10303",
                    "description": "",
                    "iconUrl": "https://oncprojectracking.ahrqdev.org/support-jsd/secure/viewavatar?size=xsmall&avatarId=10316&avatarType=issuetype",
                    "name": "Requirement/Non-Conformity",
                    "subtask": true,
                    "avatarId": 10316
                },
                "timespent": null,
                "project": {
                    "self": "https://oncprojectracking.ahrqdev.org/support-jsd/rest/api/2/project/10103",
                    "id": "10103",
                    "key": "R4SDR",
                    "name": "Review for Signals/Direct Review",
                    "projectTypeKey": "service_desk",
                    "avatarUrls": {
                        "48x48": "https://oncprojectracking.ahrqdev.org/support-jsd/secure/projectavatar?avatarId=10324",
                        "24x24": "https://oncprojectracking.ahrqdev.org/support-jsd/secure/projectavatar?size=small&avatarId=10324",
                        "16x16": "https://oncprojectracking.ahrqdev.org/support-jsd/secure/projectavatar?size=xsmall&avatarId=10324",
                        "32x32": "https://oncprojectracking.ahrqdev.org/support-jsd/secure/projectavatar?size=medium&avatarId=10324"
                    }
                },
                "aggregatetimespent": null,
                "customfield_10940": null,
                "customfield_10302": null,
                "customfield_10303": null,
                "customfield_10941": null,
                "customfield_10700": null,
                "customfield_10304": null,
                "customfield_10942": null,
                "customfield_10305": null,
                "customfield_10943": null,
                "customfield_10306": null,
                "customfield_10944": {
                    "self": "https://oncprojectracking.ahrqdev.org/support-jsd/rest/api/2/customFieldOption/10871",
                    "value": "No Non-Conformity Found",
                    "id": "10871"
                },
                "customfield_10307": null,
                "customfield_10945": null,
                "customfield_10308": null,
                "customfield_10946": null,
                "resolutiondate": null,
                "customfield_10309": null,
                "customfield_10947": null,
                "workratio": -1,
                "watches": {
                    "self": "https://oncprojectracking.ahrqdev.org/support-jsd/rest/api/2/issue/R4SDR-89/watchers",
                    "watchCount": 0,
                    "isWatching": false
                },
                "created": "2020-06-26T16:37:53.000+0000",
                "customfield_10300": null,
                "customfield_10412": null,
                "customfield_10413": null,
                "customfield_10930": null,
                "customfield_10931": null,
                "customfield_10932": null,
                "customfield_10933": {
                    "self": "https://oncprojectracking.ahrqdev.org/support-jsd/rest/api/2/customFieldOption/10725",
                    "value": "170.402(b)(2)",
                    "id": "10725"
                },
                "customfield_10934": null,
                "customfield_10935": null,
                "customfield_10936": {
                    "self": "https://oncprojectracking.ahrqdev.org/support-jsd/rest/api/2/customFieldOption/10792",
                    "value": "No",
                    "id": "10792"
                },
                "customfield_10937": null,
                "customfield_10938": null,
                "updated": "2020-06-30T13:29:34.000+0000",
                "timeoriginalestimate": null,
                "description": null,
                "customfield_10411": null,
                "customfield_10402": null,
                "security": {
                    "self": "https://oncprojectracking.ahrqdev.org/support-jsd/rest/api/2/securitylevel/10005",
                    "id": "10005",
                    "description": "",
                    "name": "Direct Review"
                },
                "customfield_10403": null,
                "customfield_10800": {
                    "self": "https://oncprojectracking.ahrqdev.org/support-jsd/rest/api/2/customFieldOption/10601",
                    "value": "No",
                    "id": "10601"
                },
                "customfield_10921": null,
                "customfield_10404": null,
                "customfield_10922": null,
                "customfield_10405": null,
                "customfield_10923": null,
                "customfield_10406": null,
                "customfield_10407": null,
                "customfield_10408": null,
                "customfield_10925": null,
                "customfield_10409": null,
                "customfield_10926": null,
                "customfield_10927": null,
                "customfield_10928": null,
                "customfield_10929": null,
                "summary": "Requirement of R4SDR-88",
                "customfield_10000": [],
                "customfield_10001": null,
                "customfield_10002": [],
                "customfield_10400": null,
                "environment": null,
                "customfield_10910": null,
                "customfield_10911": null,
                "customfield_10912": null,
                "duedate": null,
                "customfield_10913": null,
                "customfield_10914": null,
                "customfield_10915": null,
                "customfield_10916": null,
                "customfield_10917": null,
                "customfield_10918": null
            }
        }
    ]
}
